COPYING.txt
MANIFEST.in
README.rst
requirements.txt
setup.cfg
setup.py
etc/environments.cfg
etc/keys.cfg
etc/keys/config_ssh
etc/keys/git_ssh
etc/keys/nonsecureid_rsa
etc/keys/nonsecureid_rsa.pub
fabuloso/__init__.py
fabuloso/cli.py
fabuloso/component.py
fabuloso/config.py
fabuloso/exceptions.py
fabuloso/fabuloso.py
fabuloso/providers.py
fabuloso/shell.py
fabuloso/utils.py
fabuloso.egg-info/PKG-INFO
fabuloso.egg-info/SOURCES.txt
fabuloso.egg-info/dependency_links.txt
fabuloso.egg-info/entry_points.txt
fabuloso.egg-info/requires.txt
fabuloso.egg-info/top_level.txt