Metadata-Version: 1.1
Name: fabuloso
Version: 1.0
Summary: FABuloso is a python tool to easily organize and deploy an OpenStack architecture using Fabric
Home-page: https://github.com/StackOps/fabuloso
Author: StackOps
Author-email: developers@stackops.com
License: Apache License 2.0
Platform: UNKNOWN
Classifier: Development Status :: 5 - Production/Stable
Classifier: Environment :: Console
Classifier: Intended Audience :: Developers
Classifier: Intended Audience :: Information Technology
Classifier: Intended Audience :: System Administrators
Classifier: License :: OSI Approved :: Apache Software License
Classifier: Natural Language :: English
Classifier: Operating System :: POSIX :: Linux
Classifier: Programming Language :: Python
Classifier: Programming Language :: Python :: 2
Classifier: Programming Language :: Python :: 2.7
Classifier: Topic :: System
